{
	"info": {
		"_postman_id": "e456e155-fb06-0187-9a2a-55aa768aaed2",
		"name": "Jobs-API",
		"schema": "https://schema.getpostman.com/json/collection/v2.1.0/collection.json"
	},
	"item": [
		{
			"name": "Registering the user",
			"event": [
				{
					"listen": "test",
					"script": {
						"exec": [
							"// To create An token which can be accessed via Environment variable dynamically,\r",
							"const jsonData = pm.response.json()\r",
							"pm.globals.set(\"accessToken\", jsonData.token);"
						],
						"type": "text/javascript"
					}
				}
			],
			"request": {
				"method": "POST",
				"header": [],
				"body": {
					"mode": "raw",
					"raw": "{\r\n    \"name\": \"John\",\r\n    \"email\": \"John@gmail.com\",\r\n    \"password\": \"admin123\"\r\n}",
					"options": {
						"raw": {
							"language": "json"
						}
					}
				},
				"url": {
					"raw": "http://localhost:3000/api/v1/auth/register",
					"protocol": "http",
					"host": [
						"localhost"
					],
					"port": "3000",
					"path": [
						"api",
						"v1",
						"auth",
						"register"
					]
				}
			},
			"response": []
		},
		{
			"name": "LoginIn",
			"event": [
				{
					"listen": "test",
					"script": {
						"exec": [
							"// To create An token which can be accessed via Environment variable dynamically,\r",
							"const jsonData = pm.response.json()\r",
							"pm.globals.set(\"accessToken\", jsonData.token);\r",
							""
						],
						"type": "text/javascript"
					}
				}
			],
			"request": {
				"method": "POST",
				"header": [],
				"body": {
					"mode": "raw",
					"raw": "{\r\n    \"email\": \"maajee0703@gmail.com\",\r\n    \"password\": \"admin123\"\r\n}",
					"options": {
						"raw": {
							"language": "json"
						}
					}
				},
				"url": {
					"raw": "http://localhost:3000/api/v1/auth/login",
					"protocol": "http",
					"host": [
						"localhost"
					],
					"port": "3000",
					"path": [
						"api",
						"v1",
						"auth",
						"login"
					]
				}
			},
			"response": []
		},
		{
			"name": "Create Jobs",
			"request": {
				"auth": {
					"type": "bearer",
					"bearer": [
						{
							"key": "token",
							"value": "{{accessToken}}",
							"type": "string"
						}
					]
				},
				"method": "POST",
				"header": [],
				"body": {
					"mode": "raw",
					"raw": "{\r\n    \"company\": \"random\",\r\n    \"position\": \"random Engineer\"\r\n}",
					"options": {
						"raw": {
							"language": "json"
						}
					}
				},
				"url": {
					"raw": "http://localhost:3000/api/v1/jobs",
					"protocol": "http",
					"host": [
						"localhost"
					],
					"port": "3000",
					"path": [
						"api",
						"v1",
						"jobs"
					]
				}
			},
			"response": []
		},
		{
			"name": "Getting All Jobs",
			"request": {
				"auth": {
					"type": "bearer",
					"bearer": [
						{
							"key": "token",
							"value": "{{accessToken}}",
							"type": "string"
						}
					]
				},
				"method": "GET",
				"header": [],
				"url": {
					"raw": "http://localhost:3000/api/v1/jobs",
					"protocol": "http",
					"host": [
						"localhost"
					],
					"port": "3000",
					"path": [
						"api",
						"v1",
						"jobs"
					]
				}
			},
			"response": []
		},
		{
			"name": "Getting a single job",
			"request": {
				"auth": {
					"type": "bearer",
					"bearer": [
						{
							"key": "token",
							"value": "{{accessToken}}",
							"type": "string"
						}
					]
				},
				"method": "GET",
				"header": [],
				"url": {
					"raw": "http://localhost:3000/api/v1/jobs/6177afab0f1dae1ae4633e2b",
					"protocol": "http",
					"host": [
						"localhost"
					],
					"port": "3000",
					"path": [
						"api",
						"v1",
						"jobs",
						"6177afab0f1dae1ae4633e2b"
					]
				}
			},
			"response": []
		},
		{
			"name": "Updating a job",
			"request": {
				"auth": {
					"type": "bearer",
					"bearer": [
						{
							"key": "token",
							"value": "{{accessToken}}",
							"type": "string"
						}
					]
				},
				"method": "PATCH",
				"header": [],
				"body": {
					"mode": "raw",
					"raw": "{\r\n    \"company\": \"Flipkart\",\r\n    \"position\": \"Cheif Executive Officer.\"\r\n}",
					"options": {
						"raw": {
							"language": "json"
						}
					}
				},
				"url": {
					"raw": "http://localhost:3000/api/v1/jobs/6177afab0f1dae1ae4633e2b",
					"protocol": "http",
					"host": [
						"localhost"
					],
					"port": "3000",
					"path": [
						"api",
						"v1",
						"jobs",
						"6177afab0f1dae1ae4633e2b"
					]
				}
			},
			"response": []
		},
		{
			"name": "Getting All Jobs",
			"request": {
				"auth": {
					"type": "bearer",
					"bearer": [
						{
							"key": "token",
							"value": "{{accessToken}}",
							"type": "string"
						}
					]
				},
				"method": "GET",
				"header": [],
				"url": {
					"raw": "http://localhost:3000/api/v1/jobs",
					"protocol": "http",
					"host": [
						"localhost"
					],
					"port": "3000",
					"path": [
						"api",
						"v1",
						"jobs"
					]
				}
			},
			"response": []
		},
		{
			"name": "Deleting a Job",
			"request": {
				"auth": {
					"type": "bearer",
					"bearer": [
						{
							"key": "token",
							"value": "{{accessToken}}",
							"type": "string"
						}
					]
				},
				"method": "DELETE",
				"header": [],
				"url": {
					"raw": "http://localhost:3000/api/v1/jobs/6177d31c3311de17c451268b",
					"protocol": "http",
					"host": [
						"localhost"
					],
					"port": "3000",
					"path": [
						"api",
						"v1",
						"jobs",
						"6177d31c3311de17c451268b"
					]
				}
			},
			"response": []
		}
	]
}